<Properties StartupConfiguration="{53E72B75-D01B-42E2-8193-0D5F7BAB2379}|https">
  <MultiItemStartupConfigurations />
  <MonoDevelop.Ide.DebuggingService.PinnedWatches />
  <MonoDevelop.Ide.ItemProperties.CarRentalAppMvc PreferredExecutionTarget="/Applications/Google Chrome.app" />
  <MonoDevelop.Ide.DebuggingService.Breakpoints>
    <BreakpointStore />
  </MonoDevelop.Ide.DebuggingService.Breakpoints>
  <MonoDevelop.Ide.Workbench ActiveDocument="CarRentalAppMvc/wwwroot/css/style.css">
    <Files>
      <File FileName="CarRentalAppMvc/Controllers/HomeController.cs" Line="93" Column="1" />
      <File FileName="CarRentalAppMvc/Views/Home/ViewVehicles.cshtml" />
      <File FileName="CarRentalAppMvc/Views/Account/Login.cshtml" Line="1" Column="1" />
      <File FileName="CarRentalAppMvc/Views/Account/Register.cshtml" Line="63" Column="19" />
      <File FileName="CarRentalAppMvc/Views/Shared/_Layout.cshtml" Line="42" Column="20" />
      <File FileName="CarRentalAppMvc/Controllers/AccountController.cs" Line="71" Column="41" />
      <File FileName="CarRentalAppMvc/wwwroot/css/style.css" Line="178" Column="1" />
    </Files>
    <Pads>
      <Pad Id="ProjectPad">
        <State name="__root__">
          <Node name="CarRentalAppMvc">
            <Node name="CarRentalAppMvc">
              <Node name="Models" expanded="True" />
              <Node name="Views" expanded="True">
                <Node name="Account" expanded="True" />
                <Node name="Home" expanded="True" />
                <Node name="Shared" expanded="True" />
                <Node name="Vehicle" expanded="True" />
              </Node>
              <Node name="wwwroot" expanded="True">
                <Node name="css" expanded="True">
                  <Node name="style.css" selected="True" />
                </Node>
              </Node>
            </Node>
          </Node>
        </State>
      </Pad>
    </Pads>
  </MonoDevelop.Ide.Workbench>
  <MonoDevelop.Ide.Workspace ActiveConfiguration="Debug" />
</Properties>